{
    "id": 57436521,
    "name": "shimmy shimmy yah",
    "author": "xswish",
    "creators": ["xswish"],
    "verifier": "xswish",
    "verification": "https://medal.tv/games/roblox/clips/jR2UzFrBSYNKwcv8O?invite=cr-MSxFYXksMzY0NTQ3NDI4",
    "percentToQualify": 30,
    "password": "Not Copyable",
    "records": [
        {
            "user": "xswish",
            "link": "https://medal.tv/games/roblox/clips/jR2UzFrBSYNKwcv8O?invite=cr-MSxFYXksMzY0NTQ3NDI4",
            "percent": 100,
            "hz": 240
        }
    ]
}
